{
	"info": {
		"_postman_id": "ae2392ec-d95e-495a-9dae-b9504f28e5fb",
		"name": "Manhattan Cinema",
		"schema": "https://schema.getpostman.com/json/collection/v2.1.0/collection.json",
		"_exporter_id": "15118186"
	},
	"item": [
		{
			"name": "login",
			"event": [
				{
					"listen": "test",
					"script": {
						"exec": [
							"const jsonResponse = pm.response.json();",
							"pm.globals.set(\"bearerToken\", jsonResponse.jwt); "
						],
						"type": "text/javascript",
						"packages": {}
					}
				}
			],
			"request": {
				"method": "POST",
				"header": [
					{
						"key": "Content-Type",
						"value": "application/json"
					}
				],
				"body": {
					"mode": "raw",
					"raw": "{\"username\": \"admin\", \"password\": \"admin\"}",
					"options": {
						"raw": {
							"language": "json"
						}
					}
				},
				"url": {
					"raw": "http://localhost:8080/login",
					"protocol": "http",
					"host": [
						"localhost"
					],
					"port": "8080",
					"path": [
						"login"
					]
				}
			},
			"response": []
		},
		{
			"name": "Create Room",
			"request": {
				"auth": {
					"type": "bearer",
					"bearer": [
						{
							"key": "token",
							"value": "{{bearerToken}}",
							"type": "string"
						}
					]
				},
				"method": "POST",
				"header": [],
				"body": {
					"mode": "raw",
					"raw": "{\n    \"cinemaId\": 1,\n    \"length\": 5,\n    \"width\": 5\n}",
					"options": {
						"raw": {
							"language": "json"
						}
					}
				},
				"url": {
					"raw": "http://localhost:8080/api/admin/room",
					"protocol": "http",
					"host": [
						"localhost"
					],
					"port": "8080",
					"path": [
						"api",
						"admin",
						"room"
					]
				}
			},
			"response": []
		},
		{
			"name": "Get All Rooms",
			"request": {
				"method": "GET",
				"header": []
			},
			"response": []
		},
		{
			"name": "Get Available Seats",
			"request": {
				"method": "GET",
				"header": []
			},
			"response": []
		},
		{
			"name": "Reserve Seat",
			"request": {
				"auth": {
					"type": "bearer",
					"bearer": [
						{
							"key": "token",
							"value": "{{bearerToken}}",
							"type": "string"
						}
					]
				},
				"method": "POST",
				"header": [],
				"url": {
					"raw": "http://localhost:8080/api/seating/reserve-seat?roomId=4&row=4&col=3",
					"protocol": "http",
					"host": [
						"localhost"
					],
					"port": "8080",
					"path": [
						"api",
						"seating",
						"reserve-seat"
					],
					"query": [
						{
							"key": "roomId",
							"value": "4"
						},
						{
							"key": "row",
							"value": "4"
						},
						{
							"key": "col",
							"value": "3"
						}
					]
				}
			},
			"response": []
		},
		{
			"name": "Cancel Seat",
			"request": {
				"auth": {
					"type": "bearer",
					"bearer": [
						{
							"key": "token",
							"value": "{{bearerToken}}",
							"type": "string"
						}
					]
				},
				"method": "POST",
				"header": [],
				"url": {
					"raw": "http://localhost:8080/api/seating/reserve-seat?roomId=4&row=4&col=3",
					"protocol": "http",
					"host": [
						"localhost"
					],
					"port": "8080",
					"path": [
						"api",
						"seating",
						"reserve-seat"
					],
					"query": [
						{
							"key": "roomId",
							"value": "4"
						},
						{
							"key": "row",
							"value": "4"
						},
						{
							"key": "col",
							"value": "3"
						}
					]
				}
			},
			"response": []
		}
	]
}